estival/__init__.py
estival/model.py
estival/priors.py
estival/sampling/__init__.py
estival/sampling/tools.py
estival/targets.py
estival/utils/__init__.py
estival/utils/parallel.py
estival/utils/sample.py
estival/wrappers/__init__.py
estival/wrappers/nevergrad.py
estival/wrappers/pymc.py
estival-0.5.2.dist-info/LICENSE
estival-0.5.2.dist-info/METADATA
estival-0.5.2.dist-info/WHEEL
estival-0.5.2.dist-info/RECORD
