Metadata-Version: 2.1
Name: estival
Version: 0.5.2
Summary: A set of calibration and probabilistic programming tools for use with summerepi2
Home-page: https://github.com/monash-emu/estival
License: BSD-2-Clause
Keywords: calibration,optimization,bayesian,compartmental modelling,summerepi
Author: David Shipman
Author-email: dshipman@gmail.com
Requires-Python: >=3.8.0,<4.0.0
Classifier: License :: OSI Approved :: BSD License
Classifier: Programming Language :: Python :: 3
Classifier: Programming Language :: Python :: 3.8
Classifier: Programming Language :: Python :: 3.9
Classifier: Programming Language :: Python :: 3.10
Classifier: Programming Language :: Python :: 3.11
Classifier: Programming Language :: Python :: 3.12
Provides-Extra: nevergrad
Provides-Extra: pymc
Requires-Dist: arviz (>=0.12.1)
Requires-Dist: cloudpickle (>=2.2.1)
Requires-Dist: nevergrad (>=0.6.0) ; extra == "nevergrad"
Requires-Dist: numpy (>=1.20.3)
Requires-Dist: pymc (>=5.2.0) ; extra == "pymc"
Requires-Dist: scipy (>=1.7.3)
Requires-Dist: summerepi2 (>=1.2.6)
Requires-Dist: tensorflow-probability (>=0.9.0)
Project-URL: Documentation, https://github.com/monash-emu/estival
Project-URL: Repository, https://github.com/monash-emu/estival
